streamlit_crewai_process_output/__init__.py
streamlit_crewai_process_output/process_output.py
tests/__init__.py
tests/conftest.py
tests/test_process_output.py
streamlit_crewai_process_output-0.1.1.dist-info/LICENSE
streamlit_crewai_process_output-0.1.1.dist-info/METADATA
streamlit_crewai_process_output-0.1.1.dist-info/WHEEL
streamlit_crewai_process_output-0.1.1.dist-info/top_level.txt
streamlit_crewai_process_output-0.1.1.dist-info/RECORD
