Metadata-Version: 2.2
Name: streamlit-crewai-process-output
Version: 0.1.1
Summary: A component for displaying CrewAI agent process outputs in Streamlit applications
Home-page: https://github.com/tonykipkemboi/streamlit-crewai-process-output
Author: Tony Kipkemboi
Author-email: iamtonykipkemboi@gmail.com
Project-URL: Bug Tracker, https://github.com/tonykipkemboi/streamlit-crewai-process-output/issues
Project-URL: Source Code, https://github.com/tonykipkemboi/streamlit-crewai-process-output
Classifier: Development Status :: 3 - Alpha
Classifier: Intended Audience :: Developers
Classifier: License :: OSI Approved :: MIT License
Classifier: Programming Language :: Python :: 3
Classifier: Programming Language :: Python :: 3.10
Classifier: Programming Language :: Python :: 3.11
Classifier: Programming Language :: Python :: 3.12
Requires-Python: >=3.10,<3.13
License-File: LICENSE
Requires-Dist: streamlit>=1.41.0
Requires-Dist: crewai>=0.95.0
Requires-Dist: crewai-tools>=0.25.8
Provides-Extra: dev
Requires-Dist: pytest>=7.0.0; extra == "dev"
Requires-Dist: pytest-asyncio>=0.21.0; extra == "dev"
Requires-Dist: pytest-cov>=4.1.0; extra == "dev"
Dynamic: author
Dynamic: author-email
Dynamic: classifier
Dynamic: description
Dynamic: description-content-type
Dynamic: home-page
Dynamic: project-url
Dynamic: provides-extra
Dynamic: requires-dist
Dynamic: requires-python
Dynamic: summary
